build_locked.py
pdm_buildlocked-0.3.0.dist-info/entry_points.txt
pdm_buildlocked-0.3.0.dist-info/WHEEL
pdm_buildlocked-0.3.0.dist-info/METADATA
pdm_buildlocked-0.3.0.dist-info/RECORD
