Metadata-Version: 2.1
Name: pdm-buildlocked
Version: 0.3.0
Summary: Adds the ability to build the project using locked dependencies.
License: MIT
Author-email: Chase Sterling <chase.sterling@gmail.com>
Requires-Python: >=3.7
Requires-Dist: pdm>=2.3.0
